{"TopicId":105290,"ForumId":69,"TopicTitle":"FPS drop","CreatedByName":"nikolay-spb","CreatedById":135182,"CreatedDateTime":"2015-04-27T19:46:39Z","PageNum":1,"Articles":[{"CreatedByName":"nikolay-spb","CreatedById":135182,"CreatedDateTime":"2015-04-27T19:46:39Z","Content":"\n\u003Cp\u003EHello all, on both 0.90 and 1.0 versions i didnt touch graphic settings, 0.90 works fine, but 1.0 has very low FPS. I tried to lower everything, only anti-aliasing helps little, but game is still very bad on FPS \u003Cimg src=\u0022//kerbal-forum-uploads.s3.us-west-2.amazonaws.com/emoticons/default_k_sad.gif\u0022 alt=\u0022:(\u0022\u003E\u003C/p\u003E\n"},{"CreatedByName":"Caelib","CreatedById":59329,"CreatedDateTime":"2015-04-27T19:53:59Z","Content":"\n\u003Cp\u003ECheck to make sure settings weren\u0027t reverted ... I\u0027ve noticed in previous updates that sometimes the game\u0027s config file can get reverted.\u003C/p\u003E\n"},{"CreatedByName":"soulsource","CreatedById":110576,"CreatedDateTime":"2015-04-27T20:13:54Z","Content":"\n\u003Cp\u003EFor me the worst FPS hog is Aero effects. You can try switching them off.\u003C/p\u003E\n"},{"CreatedByName":"tempsgk","CreatedById":134343,"CreatedDateTime":"2015-04-27T20:24:56Z","Content":"\n\u003Cp\u003EYes got this as well. 1.0 has no doubt worst performance.\u003C/p\u003E\n"},{"CreatedByName":"metl","CreatedById":82406,"CreatedDateTime":"2015-04-27T20:25:02Z","Content":"\n\u003Cp\u003EI\u0027m actually getting double fps with higher settings.\u003C/p\u003E\n"},{"CreatedByName":"Eric S","CreatedById":57117,"CreatedDateTime":"2015-04-27T21:10:51Z","Content":"\n\u003Cp\u003EAre you playing with mods? Mods that weren\u0027t updated to 1.0 (or where incorrectly updated to 1.0) can throw a lot of errors, which really slows things down.\u003C/p\u003E\n"},{"CreatedByName":"tempsgk","CreatedById":134343,"CreatedDateTime":"2015-04-27T21:25:05Z","Content":"\n\u003Cp\u003ENo default base game.\u003C/p\u003E\n"},{"CreatedByName":"JacobT11","CreatedById":11673,"CreatedDateTime":"2015-04-27T21:34:16Z","Content":"\n\u003Cp\u003EYep, same here. Stock .90 I could get around 45fps just sitting on the pad with a command module. Stock 1.0 is around 25fps, same settings, same situation. Even worse in the VAB. Drops to around 15fps with just a command pod.\u003C/p\u003E\n"},{"CreatedByName":"tempsgk","CreatedById":134343,"CreatedDateTime":"2015-04-27T21:41:45Z","Content":"\n\u003Cp\u003EOk so looks like it might be a bug, I\u0027m in orbit 90 km around kerbin. looking into space = 60 fps, Looking to the planet = 30 fps. Even in 0.9 I don\u0027t get this massive FPS drop.\u003C/p\u003E\u003Cp\u003EAlso I was thinking it is the launch base, but its not. Any where I am in orbit, even if I\u0027m not looking at the launch base, 30-35 fps looking into planet.\u003C/p\u003E\n\u003Cspan class=\u0022ipsType_reset ipsType_medium ipsType_light\u0022 data-excludequote=\u0022\u0022\u003E\n\u003Cstrong\u003EEdited \u003Ctime datetime=\u00222015-04-27T21:49:45Z\u0022 title=\u002204/27/2015 09:49  PM\u0022 data-short=\u00229 yr\u0022\u003EApril 27, 2015\u003C/time\u003E by tempsgk\u003C/strong\u003E\n\u003C/span\u003E\n"},{"CreatedByName":"Gkirmathal","CreatedById":135480,"CreatedDateTime":"2015-04-27T21:56:39Z","Content":"\n\u003Cblockquote data-ipsquote=\u0022\u0022 class=\u0022ipsQuote\u0022 data-ipsquote-username=\u0022tempsgk\u0022 data-cite=\u0022tempsgk\u0022\u003E\u003Cdiv\u003EOk so looks like it might be a bug, I\u0027m in orbit 90 km around kerbin. looking into space = 60 fps, Looking to the planet = 30 fps. Even in 0.9 I don\u0027t get this massive FPS drop.\u003Cp\u003EAlso I was thinking it is the launch base, but its not. Any where I am in orbit, even if I\u0027m not looking at the launch base, 30-35 fps looking into planet.\u003C/p\u003E\u003C/div\u003E\u003C/blockquote\u003E\u003Cp\u003EI cannot comment on this atm as im still updating. But this sounds like the ocean-render issue 0.9 had. Thought SQUAD had this fixed...\u003C/p\u003E\n"},{"CreatedByName":"Galileo Kerbonaut","CreatedById":65299,"CreatedDateTime":"2015-04-27T21:56:44Z","Content":"\n\u003Cp\u003EI just did a quick FPS test with the largest stock rocket. I believe it has 78 parts. \u003C/p\u003E\u003Cp\u003EVAB 60 FPS\u003C/p\u003E\u003Cp\u003ELaunchpad 60 FPS\u003C/p\u003E\u003Cp\u003EFlight 60 FPS\u003C/p\u003E\u003Cp\u003EFlight \u002B Aero effects 45 FPS\u003C/p\u003E\u003Cp\u003ESpace 60 FPS\u003C/p\u003E\u003Cp\u003EReturn through atmosphere 45 FPS\u003C/p\u003E\u003Cp\u003ERadeon R7950 3gb / I5 / 6 gb RAM / 1920x1080 / graphics settings all maxed out\u003C/p\u003E\n\u003Cspan class=\u0022ipsType_reset ipsType_medium ipsType_light\u0022 data-excludequote=\u0022\u0022\u003E\n\u003Cstrong\u003EEdited \u003Ctime datetime=\u00222015-04-27T22:04:36Z\u0022 title=\u002204/27/2015 10:04  PM\u0022 data-short=\u00229 yr\u0022\u003EApril 27, 2015\u003C/time\u003E by Galileo Kerbonaut\u003C/strong\u003E\n\u003C/span\u003E\n"},{"CreatedByName":"NovaSilisko","CreatedById":3897,"CreatedDateTime":"2015-04-27T21:58:26Z","Content":"\n\u003Cp\u003EThe biggest suspect for newfound FPS loss would be the aerodynamic calculations, I think. Especially if it\u0027s being done on a single thread as most other things in KSP.\u003C/p\u003E\n"},{"CreatedByName":"nikolay-spb","CreatedById":135182,"CreatedDateTime":"2015-04-27T22:03:28Z","Content":"\n\u003Cp\u003Ei found that if you put renderer quality to \u0022fastest\u0022 it will do much better, but still not as near as 0.90\u003C/p\u003E\n"},{"CreatedByName":"bsimms606","CreatedById":131428,"CreatedDateTime":"2015-04-28T00:32:51Z","Content":"\n\u003Cp\u003ECrazy thing about my install, the performance is almost unplayable unless I MAX all the graphics settings, then it runs super smooth. I\u0027m not gonna argue with it, though.\u003C/p\u003E\n"},{"CreatedByName":"thorfinn","CreatedById":8349,"CreatedDateTime":"2015-04-28T00:45:21Z","Content":"\n\u003Cblockquote data-ipsquote=\u0022\u0022 class=\u0022ipsQuote\u0022 data-ipsquote-username=\u0022NovaSilisko\u0022 data-cite=\u0022NovaSilisko\u0022\u003E\u003Cdiv\u003EThe biggest suspect for newfound FPS loss would be the aerodynamic calculations, I think. Especially if it\u0027s being done on a single thread as most other things in KSP.\u003C/div\u003E\u003C/blockquote\u003E\u003Cp\u003EWhat I can see is the usual stark difference in FPS between looking into space (timer solidly in the green) and looking at the ground (yellow shows up even with a 10 part ship). This has existed for a very long time, I can\u0027t really tell if it got even worse because the memory leaks on OSX are making my game crash evey 20 minutes. I am seriously disappointed with this update.\u003C/p\u003E\n"},{"CreatedByName":"tempsgk","CreatedById":134343,"CreatedDateTime":"2015-04-28T03:44:04Z","Content":"\n\u003Cp\u003EIts worst, 60 fps to 30 fps just by looking at the planet is ridiculous. I can tell you I don\u0027t have this problem in 0.9. Also I forgot to mention my ship is a small stock space plane. Which makes it even worst! \u003C/p\u003E\u003Cp\u003EThis is one of the lag problem. The other lag problem is the aero effects especially when reaching mach speed at high altitudes.\u003C/p\u003E\u003Cp\u003EOverall, looks like squad missed its mark here with optimisation. The loading times are great by the way, but on the other hand the terrible optimisation might be to do with the change of texture formats.\u003C/p\u003E\n\u003Cspan class=\u0022ipsType_reset ipsType_medium ipsType_light\u0022 data-excludequote=\u0022\u0022\u003E\n\u003Cstrong\u003EEdited \u003Ctime datetime=\u00222015-04-28T03:49:02Z\u0022 title=\u002204/28/2015 03:49  AM\u0022 data-short=\u00229 yr\u0022\u003EApril 28, 2015\u003C/time\u003E by tempsgk\u003C/strong\u003E\n\u003C/span\u003E\n"},{"CreatedByName":"Morrigi","CreatedById":25077,"CreatedDateTime":"2015-04-28T04:16:53Z","Content":"\n\u003Cp\u003EI\u0027m also getting much worse performance on this version than any of the previous ones.\u003C/p\u003E\n"},{"CreatedByName":"thorfinn","CreatedById":8349,"CreatedDateTime":"2015-04-28T09:49:33Z","Content":"\n\u003Cblockquote data-ipsquote=\u0022\u0022 class=\u0022ipsQuote\u0022 data-ipsquote-username=\u0022Gkirmathal\u0022 data-cite=\u0022Gkirmathal\u0022\u003E\u003Cdiv\u003EI cannot comment on this atm as im still updating. But this sounds like the ocean-render issue 0.9 had. Thought SQUAD had this fixed...\u003C/div\u003E\u003C/blockquote\u003E\u003Cp\u003EI remember discussing a similar situation (framerate going down the drain when Kerbin was in the viewport) when I still was on the experimentals team, and that was, like... three years ago.\u003C/p\u003E\n"},{"CreatedByName":"MWJ","CreatedById":62258,"CreatedDateTime":"2015-04-28T09:50:54Z","Content":"\n\u003Cp\u003ECan confirm this,\u003C/p\u003E\u003Cp\u003Equite smooth with over 500 Parts on\u003C/p\u003E\u003Cp\u003Ei7-4930K and R280X / 32GB\u003C/p\u003E\u003Cp\u003Ein 0.90, unplayable performance with stock Aeris on Runway in 1.0 with same settings on new install and save.\u003C/p\u003E\u003Cp\u003Eedit: spellcheck\u003C/p\u003E\n\u003Cspan class=\u0022ipsType_reset ipsType_medium ipsType_light\u0022 data-excludequote=\u0022\u0022\u003E\n\u003Cstrong\u003EEdited \u003Ctime datetime=\u00222015-04-28T09:53:26Z\u0022 title=\u002204/28/2015 09:53  AM\u0022 data-short=\u00229 yr\u0022\u003EApril 28, 2015\u003C/time\u003E by MWJ\u003C/strong\u003E\n\u003C/span\u003E\n"},{"CreatedByName":"diego_gz","CreatedById":116469,"CreatedDateTime":"2015-04-28T11:09:41Z","Content":"\n\u003Cp\u003EI am having this problem too. I am using linux and I updated from 0.25. I use an i7-4702MQ with Intel HD4600. I know that it is not exactly a high-end pc for gaming but in 0.25, with tons of mods (RemoteTech, Interstellar, Mechjeb, DeadlyReentry, FAR,Environmental Visual Enhancements , life support, KAS, InfernalRobotics, HotRockets, ScanSat, realchute, alarm clock, etc, etc) I had an slightly better performance than the stock 1.0. In 0.25 stock it worked just fine.\u003C/p\u003E\u003Cp\u003EI am also noticing that, flying a plane, if I look to the sky, the game works super smooth, if I look to the ground I have a massive FPS drop. I am using medium settings without AA.\u003C/p\u003E\n"},{"CreatedByName":"MWJ","CreatedById":62258,"CreatedDateTime":"2015-04-28T11:17:24Z","Content":"\n\u003Cp\u003EMy problem now seems completely gone after restarting and turning the render settings from highest setting to beautiful and anti-aliasing from 4x to 2x... strange. (Anti Aliasing 8x creates a blurred (like gaussian blur) slideshow, rendering text completely unreadable.)\u003C/p\u003E\n"},{"CreatedByName":"tempsgk","CreatedById":134343,"CreatedDateTime":"2015-05-03T05:56:23Z","Content":"\n\u003Cp\u003ELooks like the FPS drop still isn\u0027t fixed with 1.02.\u003C/p\u003E\n"},{"CreatedByName":"Baleur","CreatedById":9954,"CreatedDateTime":"2015-09-14T16:49:59Z","Content":"\n\u003Cp\u003EAnd today still isnt fixed with 1.0.4\u003C/p\u003E\n"}]}