{"TopicId":177596,"ForumId":55,"TopicTitle":"Grouping parts","CreatedByName":"Cheif Operations Director","CreatedById":183218,"CreatedDateTime":"2018-08-16T04:03:29Z","PageNum":1,"Articles":[{"CreatedByName":"Cheif Operations Director","CreatedById":183218,"CreatedDateTime":"2018-08-16T04:03:29Z","Content":"\n\u003Cp\u003E\nSometimes when I\u0027m making a large rocket the lag of my slow laptop is agonising. My concept is that each part can be grouped into one large part so the game only needs to \u0022calculate\u0022 the physics on that one part. This is also useful for dealing with large payloads.\u00A0\n\u003C/p\u003E\n"},{"CreatedByName":"Lisias","CreatedById":187168,"CreatedDateTime":"2018-08-16T05:59:22Z","Content":"\n\u003Cp\u003E\nTry Ubiowelding.\u00A0 It \u0022welds\u0022 parts together, doing exactly what you wants.\n\u003C/p\u003E\n\u003Cp\u003E\nNot all parts can be welded together (docking ports sometimes has glitches when welded), but it helps a lot with the parts that can.\n\u003C/p\u003E\n"}]}